LICENSE
MANIFEST.in
README.rst
setup.py
django_github.egg-info/PKG-INFO
django_github.egg-info/SOURCES.txt
django_github.egg-info/dependency_links.txt
django_github.egg-info/requires.txt
django_github.egg-info/top_level.txt
github/__init__.py
github/admin.py
github/models.py
github/tests.py
github/urls.py
github/views.py
github/libs/__init__.py
github/libs/github.py
github/management/__init__.py
github/management/commands/__init__.py
github/management/commands/fetch_github.py
github/migrations/0001_initial.py
github/migrations/0002_add_user_model.py
github/migrations/0003_unique_together.py
github/migrations/0004_add_gists_and_languages.py
github/migrations/0005_add_author_to_commit.py
github/migrations/0006_user_rename.py
github/migrations/0007_watched_followers.py
github/migrations/__init__.py
github/templates/base.html
github/templates/github/base_github.html
github/templates/github/blob_detail.html
github/templates/github/blob_list.html
github/templates/github/commit_list.html
github/templates/github/gist_detail.html
github/templates/github/gist_list.html
github/templates/github/project_detail.html
github/templates/github/project_list.html
github/templates/github/user_detail.html
github/templates/github/user_list.html